setup.py
landmark_ml/__init__.py
landmark_ml/runclustering.py
landmark_ml.egg-info/PKG-INFO
landmark_ml.egg-info/SOURCES.txt
landmark_ml.egg-info/dependency_links.txt
landmark_ml.egg-info/requires.txt
landmark_ml.egg-info/top_level.txt
landmark_ml/extraction/ExtractionCheck.py
landmark_ml/extraction/__init__.py
landmark_ml/learning/DivListLearner.py
landmark_ml/learning/ListLearner.py
landmark_ml/learning/OptionalRuleLearnerScript.py
landmark_ml/learning/PageClusterer.py
landmark_ml/learning/PageManager.py
landmark_ml/learning/RuleEval.py
landmark_ml/learning/RuleLearner.py
landmark_ml/learning/RuleLearnerAllSlots.py
landmark_ml/learning/RuleLearnerAndExtraction.py
landmark_ml/learning/SlotComparator.py
landmark_ml/learning/Stripes.py
landmark_ml/learning/Tree.py
landmark_ml/learning/TreeListLearner.py
landmark_ml/learning/TreeNode.py
landmark_ml/learning/TruffleShuffle.py
landmark_ml/learning/__init__.py
landmark_ml/scripts/April2016QPRTrain.py
landmark_ml/scripts/LearningOnProjectFolder.py
landmark_ml/scripts/PrintSlots.py
landmark_ml/scripts/PrintStripes.py
landmark_ml/scripts/TextLocation.py
landmark_ml/scripts/ValidBoundingStripes.py
landmark_ml/scripts/__init__.py
landmark_ml/scripts/cluster_diff.py
landmark_ml/scripts/get_all_pages_for_sites_for_groundtruth.py
landmark_ml/scripts/get_k_pages_for_sites.py
landmark_ml/scripts/jl_to_html_and_json.py
landmark_ml/scripts/step_00_jl_to_cluster_input_files.py
landmark_ml/scripts/step_01_manual_rules_to_extrations.py
landmark_ml/scripts/step_01_rules_to_extrations.py
landmark_ml/scripts/step_02b_top_clusters_to_gui.py
landmark_ml/scripts/step_03b_tld_rules_to_extractions.py
landmark_ml/scripts/undercrawler_to_json_files.py
landmark_ml/util/PageManagementUtilities.py
landmark_ml/util/__init__.py