Metadata-Version: 1.1
Name: landmark-ml
Version: 0.1.1
Summary: Machine learning library for the landmark set of tools
Home-page: https://github.com/inferlink/landmark-ml
Author: InferLink
Author-email: developers@inferlink.com 
License: GNU AGPL
Download-URL: https://github.com/inferlink/landmark-ml
Platform: UNKNOWN
